README.md
setup.cfg
setup.py
release_name_generator/__init__.py
release_name_generator/config.py
release_name_generator/main.py
release_name_generator/names_generator.py
release_name_generator/tasks.py
release_name_generator.egg-info/PKG-INFO
release_name_generator.egg-info/SOURCES.txt
release_name_generator.egg-info/dependency_links.txt
release_name_generator.egg-info/entry_points.txt
release_name_generator.egg-info/requires.txt
release_name_generator.egg-info/top_level.txt
release_name_generator/common/__init__.py
release_name_generator/common/utils.py