Metadata-Version: 1.1
Name: release-name-generator
Version: 0.0.1
Summary: To generate milestone name
Home-page: https://github.com/smbdsbrain/markov-experiments
Author: Pavel Kolodkin
Author-email: pavel@kolodkin.com
License: MIT License
Platform: UNKNOWN
Classifier: Programming Language :: Python :: 3
Classifier: License :: OSI Approved :: MIT License
Classifier: Operating System :: OS Independent
